tray_taskmgr/__init__.py
tray_taskmgr-0.0.1.dist-info/METADATA
tray_taskmgr-0.0.1.dist-info/WHEEL
tray_taskmgr-0.0.1.dist-info/entry_points.txt
tray_taskmgr-0.0.1.dist-info/top_level.txt
tray_taskmgr-0.0.1.dist-info/RECORD
